[[2.216497,{"lines":{"0":[["                                                                                ",{}]],"1":[["                                                                                ",{}]],"2":[["                                                                                ",{}]],"3":[["                                                                                ",{}]],"4":[["                                                                                ",{}]],"5":[["                                                                                ",{}]],"6":[["                                                                                ",{}]],"7":[["                                                                                ",{}]],"8":[["                                                                                ",{}]],"9":[["                                                                                ",{}]],"10":[["                                                                                ",{}]],"11":[["                                                                                ",{}]],"12":[["                                                                                ",{}]],"13":[["                                                                                ",{}]],"14":[["                                                                                ",{}]],"15":[["                                                                                ",{}]],"16":[["                                                                                ",{}]],"17":[["                                                                                ",{}]],"18":[["                                                                                ",{}]],"19":[["                                                                                ",{}]],"20":[["                                                                                ",{}]],"21":[["                                                                                ",{}]],"22":[["                                                                                ",{}]],"23":[["                                                                                ",{}]]},"cursor":{"x":0,"y":0,"visible":true}}],[0.228095,{}],[0.0009660000000000001,{"lines":{"0":[["daniel",{"fg":4,"bold":true}],["@rarity ",{}],["~",{"bold":true}],[" %                                                               ",{}]]},"cursor":{"x":18}}],[0.778292,{"lines":{"0":[["daniel",{"fg":4,"bold":true}],["@rarity ",{}],["~",{"bold":true}],[" % t                                                             ",{}]]},"cursor":{"x":19}}],[0.136082,{"lines":{"0":[["daniel",{"fg":4,"bold":true}],["@rarity ",{}],["~",{"bold":true}],[" % to                                                            ",{}]]},"cursor":{"x":20}}],[0.047473,{"lines":{"0":[["daniel",{"fg":4,"bold":true}],["@rarity ",{}],["~",{"bold":true}],[" % toi                                                           ",{}]]},"cursor":{"x":21}}],[0.29452,{"lines":{"0":[["daniel",{"fg":4,"bold":true}],["@rarity ",{}],["~",{"bold":true}],[" % toil                                                          ",{}]]},"cursor":{"x":22}}],[0.166818,{"lines":{"0":[["daniel",{"fg":4,"bold":true}],["@rarity ",{}],["~",{"bold":true}],[" % toile                                                         ",{}]]},"cursor":{"x":23}}],[0.092434,{"lines":{"0":[["daniel",{"fg":4,"bold":true}],["@rarity ",{}],["~",{"bold":true}],[" % toilet                                                        ",{}]]},"cursor":{"x":24}}],[0.137694,{"cursor":{"x":25}}],[1.146574,{"lines":{"0":[["daniel",{"fg":4,"bold":true}],["@rarity ",{}],["~",{"bold":true}],[" % toilet p                                                      ",{}]]},"cursor":{"x":26}}],[0.231863,{"lines":{"0":[["daniel",{"fg":4,"bold":true}],["@rarity ",{}],["~",{"bold":true}],[" % toilet po                                                     ",{}]]},"cursor":{"x":27}}],[0.235517,{"lines":{"0":[["daniel",{"fg":4,"bold":true}],["@rarity ",{}],["~",{"bold":true}],[" % toilet poo                                                    ",{}]]},"cursor":{"x":28}}],[0.146621,{"lines":{"0":[["daniel",{"fg":4,"bold":true}],["@rarity ",{}],["~",{"bold":true}],[" % toilet poop                                                   ",{}]]},"cursor":{"x":29}}],[1.117338,{"cursor":{"x":0,"y":1}}],[0.002611,{}],[0.169946,{"cursor":{"x":28}}],[0.002179,{"lines":{"3":[[" mmmm    mmm    mmm   mmmm                                                      ",{}]],"4":[[" #\" \"#  #\" \"#  #\" \"#  #\" \"#                                                     ",{}]],"5":[[" #   #  #   #  #   #  #   #                                                     ",{}]],"6":[[" ##m#\"  \"#m#\"  \"#m#\"  ##m#\"                                                     ",{}]],"7":[[" #                    #                                                         ",{}]],"8":[[" \"                    \"                                                         ",{}]]},"cursor":{"x":0,"y":9}}],[0.024426,{}],[0.000367,{"lines":{"9":[["daniel",{"fg":4,"bold":true}],["@rarity ",{}],["~",{"bold":true}],[" %                                                               ",{}]]},"cursor":{"x":18}}],[4.285424,{"cursor":{"x":0,"y":10}}]]